<?xml version='1.1' encoding='UTF-8'?>
<fingerprint>
  <timestamp>2023-08-25 15:04:18.207 UTC</timestamp>
  <md5sum>a0540217f1f23ff3901833a171b680ce</md5sum>
  <fileName>Credential id=InstanceIdentity name=jenkins (private key for docker ssh agent)</fileName>
  <usages/>
  <facets>
    <com.cloudbees.plugins.credentials.fingerprints.NodeCredentialsFingerprintFacet plugin="credentials@1271.v54b_1c2c6388a_">
      <timestamp>1692975858207</timestamp>
      <nodeName>docker-agent-000cnlhz0zzcr</nodeName>
      <timestamp0>1692975858207</timestamp0>
    </com.cloudbees.plugins.credentials.fingerprints.NodeCredentialsFingerprintFacet>
  </facets>
</fingerprint>